README.rst
setup.cfg
setup.py
setupy_download_helper.py
chromedriver/__init__.py
chromedriver.egg-info/PKG-INFO
chromedriver.egg-info/SOURCES.txt
chromedriver.egg-info/dependency_links.txt
chromedriver.egg-info/entry_points.txt
chromedriver.egg-info/not-zip-safe
chromedriver.egg-info/top_level.txt