Metadata-Version: 1.0
Name: chromedriver
Version: 2.21
Summary: Tool for downloading chromedriver
Home-page: UNKNOWN
Author: Maksym Shalenyi (enkidulan)
Author-email: supamaxy@gmail.com
License: apache2.0 (http://www.apache.org/licenses/LICENSE-2.0)
Keywords: chromedriver
Platform: UNKNOWN
